snakemake_executor_plugin_donau/__init__.py
snakemake_executor_plugin_donau/executor.py
snakemake_executor_plugin_donau/logging.py
snakemake_executor_plugin_donau-0.1.2.dist-info/METADATA
snakemake_executor_plugin_donau-0.1.2.dist-info/WHEEL
snakemake_executor_plugin_donau-0.1.2.dist-info/entry_points.txt
snakemake_executor_plugin_donau-0.1.2.dist-info/licenses/LICENSE
snakemake_executor_plugin_donau-0.1.2.dist-info/RECORD
