Metadata-Version: 2.4
Name: snakemake-executor-plugin-donau
Version: 0.1.2
Summary: A Snakemake executor plugin for Huawei Donau scheduler
License: MIT
License-File: LICENSE
Keywords: snakemake,plugin,executor,cluster,donau
Author: Jian Zhang zhangjian199567@outlook.com
Requires-Python: >=3.8,<4.0
Classifier: License :: OSI Approved :: MIT License
Classifier: Programming Language :: Python :: 3
Classifier: Programming Language :: Python :: 3.8
Classifier: Programming Language :: Python :: 3.9
Classifier: Programming Language :: Python :: 3.10
Classifier: Programming Language :: Python :: 3.11
Classifier: Programming Language :: Python :: 3.12
Classifier: Programming Language :: Python :: 3.13
Classifier: Programming Language :: Python :: 3.14
Requires-Dist: loguru (>=0.7.0,<0.8.0)
Requires-Dist: snakemake (>=9.0.0,<10.0.0)
Requires-Dist: snakemake-interface-common (>=1.17.1,<2.0.0)
Requires-Dist: snakemake-interface-executor-plugins (>=9.0.0,<10.0.0)
